{
  "work_id": "Bacchylides.Paeans",
  "metadata": {
    "author": "Bacchylides",
    "title": "Paeans",
    "genre": "philosophy",
    "century": -2
  },
  "prior_confidence": 0.48,
  "posterior_confidence": {
    "mean": 0.5481148070469897,
    "std": 0.1306520657131167,
    "ci_lower": 0.3010698109906406,
    "ci_upper": 0.7920411242145048,
    "median": 0.5473703983015344
  },
  "fragments_used": 2,
  "citations_used": 0,
  "reconstruction": {
    "1": "Fragment 1 from Bacchylides.Paeans describing key concepts... [confidence: 75.0%]",
    "2": "Fragment 2 from Bacchylides.Paeans describing key concepts... [confidence: 80.0%]"
  },
  "metrics": {
    "text_coverage": 0.0244,
    "citation_density": 0.0,
    "confidence_stability": 0.8693479342868833,
    "source_diversity": 0.6666666666666666,
    "overall_quality": 0.4468340495808175
  },
  "evidence_summary": {
    "fragment_evidence": 2,
    "citation_evidence": 0,
    "total_weight": 0.976
  }
}