{
  "work_id": "Archimedes.QuadratureOfParabola",
  "metadata": {
    "author": "Archimedes",
    "title": "QuadratureOfParabola",
    "genre": "philosophy",
    "century": -2
  },
  "prior_confidence": 0.48,
  "posterior_confidence": {
    "mean": 0.557578360885775,
    "std": 0.12669915918046248,
    "ci_lower": 0.3036426020566547,
    "ci_upper": 0.7945857159770922,
    "median": 0.558930908286009
  },
  "fragments_used": 2,
  "citations_used": 0,
  "reconstruction": {
    "1": "Fragment 1 from Archimedes.QuadratureOfParabola describing key concepts... [confidence: 75.0%]",
    "2": "Fragment 2 from Archimedes.QuadratureOfParabola describing key concepts... [confidence: 80.0%]"
  },
  "metrics": {
    "text_coverage": 0.0296,
    "citation_density": 0.0,
    "confidence_stability": 0.8733008408195375,
    "source_diversity": 0.6666666666666666,
    "overall_quality": 0.4525747617695971
  },
  "evidence_summary": {
    "fragment_evidence": 2,
    "citation_evidence": 0,
    "total_weight": 1.184
  }
}